{
    "info": {
        "_postman_id": "172bbcb7-6a66-449b-a42b-9538fd0c882f",
        "name": "1-b",
        "schema": "https://schema.getpostman.com/json/collection/v2.1.0/collection.json"
    },
    "item": [
        {
            "name": "Sample endpoint: Returns details about a particular user",
            "id": "2ba5cfb1-df93-4821-b4dc-b481cb3262a6",
            "request": {
                "method": "GET",
                "header": [
                    {
                        "key": "Accept",
                        "value": "application/json"
                    }
                ],
                "url": {
                    "raw": "{{baseUrl}}/user?id=-62133449",
                    "host": [
                        "{{baseUrl}}"
                    ],
                    "path": [
                        "user"
                    ],
                    "query": [
                        {
                            "key": "id",
                            "value": "-62133449",
                            "description": "(Required) ID of the user"
                        }
                    ]
                }
            },
            "response": [
                {
                    "id": "9131e7a7-16f0-432a-97c5-09f7ba1b11d1",
                    "name": "Sample response: Details about a user by ID",
                    "originalRequest": {
                        "method": "GET",
                        "header": [
                            {
                                "description": "Added as a part of security scheme: basic",
                                "key": "Authorization",
                                "value": "Basic <credentials>"
                            }
                        ],
                        "url": {
                            "raw": "{{baseUrl}}/user?id=-62133449",
                            "host": [
                                "{{baseUrl}}"
                            ],
                            "path": [
                                "user"
                            ],
                            "query": [
                                {
                                    "key": "id",
                                    "value": "-62133449"
                                }
                            ]
                        }
                    },
                    "status": "OK",
                    "code": 200,
                    "_postman_previewlanguage": "json",
                    "header": [
                        {
                            "disabled": false,
                            "description": "A link to the next page of responses",
                            "key": "x-next",
                            "value": "sit eu exercitation minim"
                        },
                        {
                            "key": "Content-Type",
                            "value": "application/json"
                        }
                    ],
                    "cookie": [],
                    "responseTime": null,
                    "body": "{\n  \"id\": -25392016,\n  \"name\": \"dolor quis ut magna\",\n  \"tag\": \"esse exercitation reprehenderit Ut et\"\n}"
                },
                {
                    "id": "3898cbfd-8466-432a-b716-f9587c8338b0",
                    "name": "Unexpected error",
                    "originalRequest": {
                        "method": "GET",
                        "header": [
                            {
                                "description": "Added as a part of security scheme: basic",
                                "key": "Authorization",
                                "value": "Basic <credentials>"
                            }
                        ],
                        "url": {
                            "raw": "{{baseUrl}}/user?id=-62133449",
                            "host": [
                                "{{baseUrl}}"
                            ],
                            "path": [
                                "user"
                            ],
                            "query": [
                                {
                                    "key": "id",
                                    "value": "-62133449"
                                }
                            ]
                        }
                    },
                    "status": "Internal Server Error",
                    "code": 500,
                    "_postman_previewlanguage": "json",
                    "header": [
                        {
                            "key": "Content-Type",
                            "value": "application/json"
                        }
                    ],
                    "cookie": [],
                    "responseTime": null,
                    "body": "{\n  \"code\": -36793851,\n  \"message\": \"veniam Lorem\"\n}"
                }
            ]
        }
    ],
    "auth": {
        "type": "basic",
        "basic": [
            {
                "key": "username",
                "value": "<Basic Auth Username>",
                "type": "string"
            },
            {
                "key": "password",
                "value": "<Basic Auth Password>",
                "type": "string"
            }
        ]
    },
    "variable": [
        {
            "id": "5e805424-6bd8-4fbc-8416-9afeeed98df3",
            "key": "baseUrl",
            "value": "localhost:3000",
            "type": "string"
        }
    ]
}